{
  "Datastore": {
    "Connection": "SqLite",

    "SqLite": {
      "Type": "SqLite",
      "ConnectionString": "Data Source=|DataDirectory|Data/GraphML.sqlite3;"
    },

    "SqlServer": {
      "Type": "SqlServer",
      "ConnectionString": "Data Source=localhost;Initial Catalog=GraphML;Integrated Security=True;MultipleActiveResultSets=True;"
    },

    "MySql": {
      "Type": "MySql",
      "ConnectionString": "server=127.0.0.1;uid=GraphML;pwd=DisruptTheMarket;database=GraphML;SslMode=none"
    }
  },
  "ImportSpecification": {
    "Organisation": "GraphML",
    "RepositoryManager": "GraphML Repository Manager",
    "Repository": "Reddit",

    "DataFile2": "../../../Sample-Data/SNAP/p2p-Gnutella08-small.txt",
    "HasHeaderRecord2": false,

    "DataFile": "../../../Sample-Data/SNAP/soc-redditHyperlinks-body-small.tsv",
    "HasHeaderRecord": true
  }
}
