{
  "defaultAssembly": "GraphML.UI.Desktop",
  "components":
  [
    {
      "type": "GraphML.UI.Desktop.RestClientFactory",
      "services":
      [
        {
          "type": "GraphML.UI.Desktop.IRestClientFactory"
        }
      ]
    },
    {
      "type": "GraphML.UI.Desktop.SyncPolicyFactory",
      "services":
      [
        {
          "type": "GraphML.UI.Desktop.ISyncPolicyFactory"
        }
      ]
    },

    {
      "type": "GraphML.UI.Desktop.RepositoryManagerServer",
      "services":
      [
        {
          "type": "GraphML.UI.Desktop.IRepositoryManagerServer"
        }
      ]
    },
    {
      "type": "GraphML.UI.Desktop.RepositoryServer",
      "services":
      [
        {
          "type": "GraphML.UI.Desktop.IRepositoryServer"
        }
      ]
    },
    {
      "type": "GraphML.UI.Desktop.GraphServer",
      "services":
      [
        {
          "type": "GraphML.UI.Desktop.IGraphServer"
        }
      ]
    },
    {
      "type": "GraphML.UI.Desktop.NodeServer",
      "services":
      [
        {
          "type": "GraphML.UI.Desktop.INodeServer"
        }
      ]
    },
    {
      "type": "GraphML.UI.Desktop.EdgeServer",
      "services":
      [
        {
          "type": "GraphML.UI.Desktop.IEdgeServer"
        }
      ]
    },
    {
      "type": "GraphML.UI.Desktop.ContactServer",
      "services":
      [
        {
          "type": "GraphML.UI.Desktop.IContactServer"
        }
      ]
    },
    {
      "type": "GraphML.UI.Desktop.OrganisationServer",
      "services":
      [
        {
          "type": "GraphML.UI.Desktop.IOrganisationServer"
        }
      ]
    },
    {
      "type": "GraphML.UI.Desktop.GraphItemAttributeServer",
      "services":
      [
        {
          "type": "GraphML.UI.Desktop.IGraphItemAttributeServer"
        }
      ]
    },
    {
      "type": "GraphML.UI.Desktop.EdgeItemAttributeServer",
      "services":
      [
        {
          "type": "GraphML.UI.Desktop.IEdgeItemAttributeServer"
        }
      ]
    },
    {
      "type": "GraphML.UI.Desktop.NodeItemAttributeServer",
      "services":
      [
        {
          "type": "GraphML.UI.Desktop.INodeItemAttributeServer"
        }
      ]
    },
    {
      "type": "GraphML.UI.Desktop.RepositoryItemAttributeServer",
      "services":
      [
        {
          "type": "GraphML.UI.Desktop.IRepositoryItemAttributeServer"
        }
      ]
    },

    {
      "type": "GraphML.UI.Desktop.AnalysisServer",
      "services":
      [
        {
          "type": "GraphML.UI.Desktop.IAnalysisServer"
        }
      ]
    },
    {
      "type": "GraphML.UI.Desktop.ResultServer",
      "services":
      [
        {
          "type": "GraphML.UI.Desktop.IResultServer"
        }
      ]
    }
  ]
}